types_versioneer-0.29.dist-info/licenses/LICENSE
versioneer-stubs/__init__.pyi
versioneer-stubs/py.typed
types_versioneer-0.29.dist-info/METADATA
types_versioneer-0.29.dist-info/WHEEL
types_versioneer-0.29.dist-info/top_level.txt
types_versioneer-0.29.dist-info/RECORD
