Metadata-Version: 2.4
Name: types-versioneer
Version: 0.29
Summary: Minimal stubs for versioneer.
Requires-Python: >=3.8
License-File: LICENSE
Dynamic: license-file
